Ints
netconf
