Metadata-Version: 2.1
Name: NETCONF-Interfaces
Version: 1.0.3
Summary: Allows Network Engineer to view interfaces details
Home-page: https://github.com/cober2019/Network-Automation/tree/master/NETCONF-YANG/NetConfInterfaces
Author: Chris Oberdalhoff
Author-email: cober91130@gmail.com
License: UNKNOWN
Platform: UNKNOWN
Classifier: Programming Language :: Python :: 3
Classifier: License :: OSI Approved :: MIT License
Classifier: Operating System :: OS Independent
Requires-Python: >=3.6
